Deeplodocus-0.3.0.data/scripts/deeplodocus-admin.py
deeplodocus/__init__.py
deeplodocus/app/__init__.py
deeplodocus/app/blocks/__init__.py
deeplodocus/app/layers/__init__.py
deeplodocus/app/layers/empty.py
deeplodocus/app/layers/flatten.py
deeplodocus/app/losses/__init__.py
deeplodocus/app/losses/cross_entropy_2d.py
deeplodocus/app/losses/yolo.py
deeplodocus/app/metrics/__init__.py
deeplodocus/app/metrics/accuracy.py
deeplodocus/app/metrics/depth.py
deeplodocus/app/metrics/image.py
deeplodocus/app/models/__init__.py
deeplodocus/app/models/alexnet.py
deeplodocus/app/models/darknet.py
deeplodocus/app/models/generic_cnns.py
deeplodocus/app/models/lenet.py
deeplodocus/app/models/vgg.py
deeplodocus/app/models/yolo.py
deeplodocus/app/optimizers/__init__.py
deeplodocus/app/transforms/__init__.py
deeplodocus/app/transforms/angles.py
deeplodocus/app/transforms/bounding_boxes.py
deeplodocus/app/transforms/generic.py
deeplodocus/app/transforms/images.py
deeplodocus/app/transforms/integers.py
deeplodocus/app/transforms/output.py
deeplodocus/app/transforms/vis.py
deeplodocus/app/transforms/yolo.py
deeplodocus/bin/__init__.py
deeplodocus/bin/deeplodocus-admin.py
deeplodocus/brain/__init__.py
deeplodocus/brain/brain.py
deeplodocus/brain/connection.py
deeplodocus/brain/frontal_lobe.py
deeplodocus/brain/signal.py
deeplodocus/brain/memory/__init__.py
deeplodocus/brain/memory/hippocampus.py
deeplodocus/brain/thalamus/__init__.py
deeplodocus/brain/thalamus/thalamus.py
deeplodocus/brain/visual_cortex/__init__.py
deeplodocus/brain/visual_cortex/graph.py
deeplodocus/brain/visual_cortex/middlewares.py
deeplodocus/brain/visual_cortex/routes.py
deeplodocus/brain/visual_cortex/views.py
deeplodocus/brain/visual_cortex/visual_cortex.py
deeplodocus/brain/visual_cortex/assets/__init__.py
deeplodocus/brain/visual_cortex/static/__init__.py
deeplodocus/brain/visual_cortex/static/css/__init__.py
deeplodocus/brain/visual_cortex/templates/__init__.py
deeplodocus/callbacks/__init__.py
Deeplodocus-0.3.0.dist-info/LICENSE
Deeplodocus-0.3.0.dist-info/LICENSE.md
Deeplodocus-0.3.0.dist-info/METADATA
Deeplodocus-0.3.0.dist-info/WHEEL
Deeplodocus-0.3.0.dist-info/entry_points.txt
Deeplodocus-0.3.0.dist-info/top_level.txt
Deeplodocus-0.3.0.dist-info/RECORD
